CHANGELOG.txt
LICENCE.txt
MANIFEST.in
README.txt
setup.py
Keyauuth/__init__.py
Keyauuth.egg-info/PKG-INFO
Keyauuth.egg-info/SOURCES.txt
Keyauuth.egg-info/dependency_links.txt
Keyauuth.egg-info/top_level.txt