Metadata-Version: 2.1
Name: Keyauuth
Version: 0.0.1
Summary: keyauuth wrappa
Home-page: 
Author: personn443
Author-email: sr.pentesters@gmail.com
License: MIT
Keywords: keyauth
Classifier: Development Status :: 5 - Production/Stable
Classifier: Intended Audience :: Education
Classifier: Operating System :: Microsoft :: Windows :: Windows 10
Classifier: License :: OSI Approved :: MIT License
Classifier: Programming Language :: Python :: 3
License-File: LICENCE.txt
